CHANGES.txt
LICENSE.txt
MANIFEST.in
README.txt
setup.py
js/__init__.py
js.angular_gettext.egg-info/PKG-INFO
js.angular_gettext.egg-info/SOURCES.txt
js.angular_gettext.egg-info/dependency_links.txt
js.angular_gettext.egg-info/entry_points.txt
js.angular_gettext.egg-info/namespace_packages.txt
js.angular_gettext.egg-info/not-zip-safe
js.angular_gettext.egg-info/requires.txt
js.angular_gettext.egg-info/top_level.txt
js/angular_gettext/__init__.py
js/angular_gettext/test_gettext.txt
js/angular_gettext/resources/angular-gettext.js
js/angular_gettext/resources/angular-gettext.min.js