Metadata-Version: 1.0
Name: js.angular-gettext
Version: 2.4.1
Summary: Fanstatic packaging of angular-gettext
Home-page: UNKNOWN
Author: Fanstatic Developers
Author-email: fanstatic@googlegroups.com
License: BSD
Platform: UNKNOWN
